ploy_ansible/__init__.py
ploy_ansible/cli1.py
ploy_ansible/conftest.py
ploy_ansible/inventory.py
ploy_ansible/inventory1.py
ploy_ansible/remote.py
ploy_ansible/test_ansible.py
ploy_ansible/test_inventory.py
ploy_ansible/ansible1_connection_plugins/execnet_connection.py
ploy_ansible/connection_plugins/__init__.py
ploy_ansible/connection_plugins/execnet_connection.py
ploy_ansible/lookup_plugins/__init__.py
ploy_ansible/lookup_plugins/ploy_crypted.py
ploy_ansible-2.0.0.dist-info/METADATA
ploy_ansible-2.0.0.dist-info/WHEEL
ploy_ansible-2.0.0.dist-info/entry_points.txt
ploy_ansible-2.0.0.dist-info/pbr.json
ploy_ansible-2.0.0.dist-info/top_level.txt
ploy_ansible-2.0.0.dist-info/RECORD
