Metadata-Version: 2.1
Name: ploy-ansible
Version: 2.0.0
Summary: Plugin to integrate Ansible with ploy.
Home-page: http://github.com/ployground/ploy_ansible
Author: Florian Schulze
Author-email: florian.schulze@gmx.net
License: GPLv3
Platform: UNKNOWN
Classifier: Environment :: Console
Classifier: Intended Audience :: System Administrators
Classifier: Programming Language :: Python :: 2.7
Classifier: Programming Language :: Python :: 3.7
Classifier: Programming Language :: Python :: 3.8
Classifier: Programming Language :: Python :: 3.9
Classifier: Programming Language :: Python :: 3.10
Classifier: Topic :: System :: Installation/Setup
Classifier: Topic :: System :: Systems Administration
Requires-Python: >=2.7, !=3.0.*, !=3.1.*, !=3.2.*, !=3.3.*, !=3.4.*, !=3.5.*, !=3.6.*
Requires-Dist: execnet
Requires-Dist: ploy (>=2.0.0)
Requires-Dist: ansible (!=2.0.*,!=2.1.*,!=2.2.*,!=2.3.*,>=1.9) ; python_version < "3.0"
Requires-Dist: ansible (>=2.4) ; python_version >= "3.0" and python_version < "3.10"
Requires-Dist: ansible-core ; python_version >= "3.10"
